osaft/__init__.py
osaft/core/__init__.py
osaft/core/backgroundfields.py
osaft/core/basecomposite.py
osaft/core/fluids.py
osaft/core/frequency.py
osaft/core/functions.py
osaft/core/geometries.py
osaft/core/helper.py
osaft/core/logger.py
osaft/core/solids.py
osaft/core/variable.py
osaft/core/version.py
osaft/core/warnings.py
osaft/plotting/__init__.py
osaft/plotting/base_plotting.py
osaft/plotting/grid.py
osaft/plotting/arf/__init__.py
osaft/plotting/arf/arf_plots.py
osaft/plotting/arf/arf_plotter.py
osaft/plotting/datacontainers/__init__.py
osaft/plotting/datacontainers/arf_datacontainer.py
osaft/plotting/datacontainers/base_velocity_datacontainer.py
osaft/plotting/datacontainers/scattering_datacontainer.py
osaft/plotting/datacontainers/wireframe_datacontainer.py
osaft/plotting/scattering/__init__.py
osaft/plotting/scattering/base_plotter.py
osaft/plotting/scattering/base_scattering_plots.py
osaft/plotting/scattering/fluid_plots.py
osaft/plotting/scattering/particle_plots.py
osaft/plotting/scattering/tri_plotter.py
osaft/plotting/scattering/wireframe_plotter.py
osaft/plotting/streaming/__init__.py
osaft/solutions/__init__.py
osaft/solutions/base_arf.py
osaft/solutions/base_scattering.py
osaft/solutions/base_solution.py
osaft/solutions/base_streaming.py
osaft/solutions/basedoinikov1994/__init__.py
osaft/solutions/basedoinikov1994/arf_general.py
osaft/solutions/basedoinikov1994/arf_limiting.py
osaft/solutions/basedoinikov1994/base.py
osaft/solutions/basedoinikov1994/scattering.py
osaft/solutions/basedoinikov2021/__init__.py
osaft/solutions/basedoinikov2021/base.py
osaft/solutions/basedoinikov2021/coefficientmatrix.py
osaft/solutions/basedoinikov2021/scattering.py
osaft/solutions/doinikov1994compressible/__init__.py
osaft/solutions/doinikov1994compressible/arf.py
osaft/solutions/doinikov1994compressible/arf_general.py
osaft/solutions/doinikov1994compressible/arf_limiting.py
osaft/solutions/doinikov1994compressible/base.py
osaft-1.3.8.dist-info/LICENSE.md
osaft-1.3.8.dist-info/METADATA
osaft-1.3.8.dist-info/WHEEL
osaft-1.3.8.dist-info/top_level.txt
osaft-1.3.8.dist-info/RECORD
