Metadata-Version: 2.1
Name: osaft
Version: 1.3.8
Summary: An Open-Source Python Library For Acoustofluidics
Author-email: gorkovpy developer team <gorkovpy@gmail.com>
License: LPGL v3
Project-URL: Documentation, https://osaft.readthedocs.io/en/latest/
Project-URL: Repository, https://gitlab.com/acoustofluidics/osaft
Project-URL: Tracker, https://gitlab.com/acoustofluidics/osaft/-/issues
Keywords: msaf,arf,scattering,acoustofluidic,acoustic-radiation-force
Classifier: Development Status :: 5 - Production/Stable
Classifier: Intended Audience :: Developers
Classifier: Intended Audience :: Education
Classifier: Intended Audience :: Science/Research
Classifier: Topic :: Scientific/Engineering :: Physics
Classifier: License :: OSI Approved :: GNU Lesser General Public License v3 (LGPLv3)
Classifier: Programming Language :: Python :: 3.9
Classifier: Programming Language :: Python :: 3.10
Classifier: Programming Language :: Python :: 3.11
Requires-Python: >=3.9
License-File: LICENSE.md
Requires-Dist: numpy (>=1.22)
Requires-Dist: scipy (>=1.8)
Requires-Dist: sympy (>=1.10)
Requires-Dist: matplotlib (>=3.5.1)
Requires-Dist: mpmath (>=1.2.0)
Provides-Extra: dev
Requires-Dist: pre-commit ; extra == 'dev'
Requires-Dist: flake8-print ; extra == 'dev'
Requires-Dist: black ; extra == 'dev'
Requires-Dist: pytest ; extra == 'dev'
Requires-Dist: pytest-cov ; extra == 'dev'
Requires-Dist: pytest-xdist ; extra == 'dev'
Requires-Dist: twine ; extra == 'dev'
Requires-Dist: build ; extra == 'dev'
Provides-Extra: docs
Requires-Dist: sphinx (>=5.0) ; extra == 'docs'
Requires-Dist: sphinx-autodoc-typehints ; extra == 'docs'
Requires-Dist: sphinx-rtd-theme ; extra == 'docs'
Requires-Dist: sphinx-copybutton ; extra == 'docs'
Requires-Dist: sphinx-gallery (>=0.11.0) ; extra == 'docs'
Requires-Dist: memory-profiler ; extra == 'docs'
Requires-Dist: furo ; extra == 'docs'
Requires-Dist: autoclasstoc ; extra == 'docs'
Requires-Dist: sphinx-autodoc-defaultargs ; extra == 'docs'
